minpycube/__init__.py
minpycube/rcube.py
minpycube-0.1.0.dist-info/METADATA
minpycube-0.1.0.dist-info/WHEEL
minpycube-0.1.0.dist-info/top_level.txt
minpycube-0.1.0.dist-info/RECORD
