Metadata-Version: 2.1
Name: minpycube
Version: 0.1.0
Summary: A minimal Python library for Rubik's Cube simulation.
Author-email: mennymendoza <jmen9575@gmail.com>
License: MIT
Requires-Python: >=3.10
